griffe_docfx-0.1.0.dist-info/METADATA
griffe_docfx-0.1.0.dist-info/WHEEL
griffe_docfx-0.1.0.dist-info/entry_points.txt
griffe_docfx-0.1.0.dist-info/licenses/LICENSE
griffe_docfx/__init__.py
griffe_docfx/__main__.py
griffe_docfx/cli.py
griffe_docfx/debug.py
griffe_docfx/py.typed
griffe_docfx-0.1.0.dist-info/RECORD
