Metadata-Version: 2.1
Name: griffe-docfx
Version: 0.1.0
Summary: Signatures for entire C# programs using docfx.
Author-Email: =?utf-8?q?Timoth=C3=A9e_Mazzucotelli?= <dev@pawamoy.fr>
License: ISC
Classifier: Development Status :: 4 - Beta
Classifier: Intended Audience :: Developers
Classifier: Programming Language :: Python
Classifier: Programming Language :: Python :: 3
Classifier: Programming Language :: Python :: 3 :: Only
Classifier: Programming Language :: Python :: 3.9
Classifier: Programming Language :: Python :: 3.10
Classifier: Programming Language :: Python :: 3.11
Classifier: Programming Language :: Python :: 3.12
Classifier: Programming Language :: Python :: 3.13
Classifier: Programming Language :: Python :: 3.14
Classifier: Topic :: Documentation
Classifier: Topic :: Software Development
Classifier: Topic :: Utilities
Classifier: Typing :: Typed
Project-URL: Homepage, https://mkdocstrings.github.io/griffe-docfx
Project-URL: Documentation, https://mkdocstrings.github.io/griffe-docfx
Project-URL: Changelog, https://mkdocstrings.github.io/griffe-docfx/changelog
Project-URL: Repository, https://github.com/mkdocstrings/griffe-docfx
Project-URL: Issues, https://github.com/mkdocstrings/griffe-docfx/issues
Project-URL: Discussions, https://github.com/mkdocstrings/griffe-docfx/discussions
Project-URL: Gitter, https://gitter.im/mkdocstrings/griffe-docfx
Project-URL: Funding, https://github.com/sponsors/pawamoy
Requires-Python: >=3.9
